ip2provider/__init__.py
ip2provider/provider.py
ip2provider/data/hostings.json
ip2provider-0.1.0.dist-info/licenses/LICENSE
ip2provider-0.1.0.dist-info/METADATA
ip2provider-0.1.0.dist-info/WHEEL
ip2provider-0.1.0.dist-info/top_level.txt
ip2provider-0.1.0.dist-info/RECORD
